orca_descriptors/__init__.py
orca_descriptors/base.py
orca_descriptors/batch_processing.py
orca_descriptors/cache.py
orca_descriptors/calculation.py
orca_descriptors/cli.py
orca_descriptors/decorators.py
orca_descriptors/descriptors/__init__.py
orca_descriptors/descriptors/electronic.py
orca_descriptors/descriptors/energy.py
orca_descriptors/descriptors/misc.py
orca_descriptors/descriptors/structural.py
orca_descriptors/descriptors/topological.py
orca_descriptors/input_generator.py
orca_descriptors/orca.py
orca_descriptors/output_parser.py
orca_descriptors/remote_cache.py
orca_descriptors/time_estimator.py
orca_descriptors-0.3.3b2.dist-info/METADATA
orca_descriptors-0.3.3b2.dist-info/WHEEL
orca_descriptors-0.3.3b2.dist-info/entry_points.txt
orca_descriptors-0.3.3b2.dist-info/licenses/LICENSE.md
orca_descriptors-0.3.3b2.dist-info/RECORD
