Metadata-Version: 2.4
Name: orca-descriptors
Version: 0.3.3b2
Summary: A Python library for automatic calculation of quantum chemical descriptors for QSAR analysis using ORCA quantum chemistry software
License: MIT
License-File: LICENSE.md
Keywords: orca,quantum-chemistry,qsar,descriptors,molecular-descriptors,computational-chemistry,dft,semi-empirical,molecular-modeling,cheminformatics
Author: MassonNN
Author-email: me@ilyalyapin.ru
Maintainer: MassonNN
Maintainer-email: me@ilyalyapin.ru
Requires-Python: >=3.10
Classifier: Development Status :: 4 - Beta
Classifier: Intended Audience :: Science/Research
Classifier: Intended Audience :: Developers
Classifier: Topic :: Scientific/Engineering :: Chemistry
Classifier: Topic :: Scientific/Engineering :: Physics
Classifier: Topic :: Software Development :: Libraries :: Python Modules
Classifier: License :: OSI Approved :: MIT License
Classifier: Programming Language :: Python :: 3
Classifier: Programming Language :: Python :: 3.10
Classifier: Programming Language :: Python :: 3.11
Classifier: Programming Language :: Python :: 3.12
Classifier: Programming Language :: Python :: 3.13
Classifier: Operating System :: OS Independent
Classifier: Natural Language :: English
Classifier: Natural Language :: Russian
Provides-Extra: pandas
Requires-Dist: numpy (>=1.20.0)
Requires-Dist: pandas (>=1.5.0) ; extra == "pandas"
Requires-Dist: rdkit (>=2023.0.0)
Requires-Dist: requests (>=2.28.0)
Project-URL: Bug Tracker, https://github.com/MassonNN/orca_descriptors/issues
Project-URL: Documentation, https://orca-descriptors.massonnn.ru
Project-URL: Homepage, https://orca-descriptors.massonnn.ru
Project-URL: Issues, https://github.com/MassonNN/orca_descriptors/issues
Project-URL: Repository, https://github.com/MassonNN/orca_descriptors
Project-URL: Source Code, https://github.com/MassonNN/orca_descriptors
